{
  "formatVersion": 1,
  "database": {
    "version": 9,
    "identityHash": "f4229686e81a0de5d2e52ec0034d7300",
    "entities": [
      {
        "tableName": "NOTES_TABLE",
        "createSql": "CREATE TABLE IF NOT EXISTS `${TABLE_NAME}` (`noteId` TEXT NOT NULL, `note_title` TEXT NOT NULL, `note_desc` TEXT NOT NULL, `date` TEXT NOT NULL, PRIMARY KEY(`noteId`))",
        "fields": [
          {
            "fieldPath": "noteId",
            "columnName": "noteId",
            "affinity": "TEXT",
            "notNull": true
          },
          {
            "fieldPath": "noteTitle",
            "columnName": "note_title",
            "affinity": "TEXT",
            "notNull": true
          },
          {
            "fieldPath": "noteTxtContent",
            "columnName": "note_desc",
            "affinity": "TEXT",
            "notNull": true
          },
          {
            "fieldPath": "date",
            "columnName": "date",
            "affinity": "TEXT",
            "notNull": true
          }
        ],
        "primaryKey": {
          "autoGenerate": false,
          "columnNames": [
            "noteId"
          ]
        }
      },
      {
        "tableName": "RECORDINGS_TABLE",
        "createSql": "CREATE TABLE IF NOT EXISTS `${TABLE_NAME}` (`recordingId` TEXT NOT NULL, `recording_number` INTEGER NOT NULL, `recording_title` TEXT, `recording_link` TEXT NOT NULL, `recording_date` TEXT NOT NULL, `recording_duration` TEXT NOT NULL, `noteId` TEXT NOT NULL, PRIMARY KEY(`recordingId`))",
        "fields": [
          {
            "fieldPath": "recordingId",
            "columnName": "recordingId",
            "affinity": "TEXT",
            "notNull": true
          },
          {
            "fieldPath": "recordingNumber",
            "columnName": "recording_number",
            "affinity": "INTEGER",
            "notNull": true
          },
          {
            "fieldPath": "recordingTitle",
            "columnName": "recording_title",
            "affinity": "TEXT"
          },
          {
            "fieldPath": "recordingLink",
            "columnName": "recording_link",
            "affinity": "TEXT",
            "notNull": true
          },
          {
            "fieldPath": "recordingDate",
            "columnName": "recording_date",
            "affinity": "TEXT",
            "notNull": true
          },
          {
            "fieldPath": "recordingDuration",
            "columnName": "recording_duration",
            "affinity": "TEXT",
            "notNull": true
          },
          {
            "fieldPath": "noteId",
            "columnName": "noteId",
            "affinity": "TEXT",
            "notNull": true
          }
        ],
        "primaryKey": {
          "autoGenerate": false,
          "columnNames": [
            "recordingId"
          ]
        }
      }
    ],
    "setupQueries": [
      "CREATE TABLE IF NOT EXISTS room_master_table (id INTEGER PRIMARY KEY,identity_hash TEXT)",
      "INSERT OR REPLACE INTO room_master_table (id,identity_hash) VALUES(42, 'f4229686e81a0de5d2e52ec0034d7300')"
    ]
  }
}